{
  "type": "Module",
  "span": {
    "start": 760,
    "end": 847
  },
  "body": [
    {
      "type": "VariableDeclaration",
      "span": {
        "start": 760,
        "end": 847
      },
      "ctxt": 0,
      "kind": "const",
      "declare": false,
      "declarations": [
        {
          "type": "VariableDeclarator",
          "span": {
            "start": 766,
            "end": 847
          },
          "id": {
            "type": "Identifier",
            "span": {
              "start": 766,
              "end": 772
            },
            "ctxt": 2,
            "value": "FooBar",
            "optional": false,
            "typeAnnotation": null
          },
          "init": {
            "type": "FunctionExpression",
            "identifier": null,
            "params": [
              {
                "type": "Parameter",
                "span": {
                  "start": 784,
                  "end": 791
                },
                "decorators": [],
                "pat": {
                  "type": "RestElement",
                  "span": {
                    "start": 784,
                    "end": 791
                  },
                  "rest": {
                    "start": 784,
                    "end": 787
                  },
                  "argument": {
                    "type": "Identifier",
                    "span": {
                      "start": 787,
                      "end": 791
                    },
                    "ctxt": 3,
                    "value": "args",
                    "optional": false,
                    "typeAnnotation": null
                  },
                  "typeAnnotation": null
                }
              }
            ],
            "decorators": [],
            "span": {
              "start": 775,
              "end": 847
            },
            "ctxt": 3,
            "body": {
              "type": "BlockStatement",
              "span": {
                "start": 793,
                "end": 847
              },
              "ctxt": 3,
              "stmts": [
                {
                  "type": "ReturnStatement",
                  "span": {
                    "start": 797,
                    "end": 845
                  },
                  "argument": {
                    "type": "CallExpression",
                    "span": {
                      "start": 804,
                      "end": 844
                    },
                    "ctxt": 0,
                    "callee": {
                      "type": "CallExpression",
                      "span": {
                        "start": 804,
                        "end": 835
                      },
                      "ctxt": 0,
                      "callee": {
                        "type": "MemberExpression",
                        "span": {
                          "start": 804,
                          "end": 819
                        },
                        "object": {
                          "type": "Identifier",
                          "span": {
                            "start": 804,
                            "end": 810
                          },
                          "ctxt": 1,
                          "value": "window",
                          "optional": false
                        },
                        "property": {
                          "type": "Identifier",
                          "span": {
                            "start": 811,
                            "end": 819
                          },
                          "value": "FSA_call"
                        }
                      },
                      "arguments": [
                        {
                          "spread": null,
                          "expression": {
                            "type": "StringLiteral",
                            "span": {
                              "start": 820,
                              "end": 824
                            },
                            "value": "ID",
                            "raw": "\"ID\""
                          }
                        },
                        {
                          "spread": null,
                          "expression": {
                            "type": "StringLiteral",
                            "span": {
                              "start": 826,
                              "end": 834
                            },
                            "value": "FooBar",
                            "raw": "\"FooBar\""
                          }
                        }
                      ],
                      "typeArguments": null
                    },
                    "arguments": [
                      {
                        "spread": {
                          "start": 836,
                          "end": 839
                        },
                        "expression": {
                          "type": "Identifier",
                          "span": {
                            "start": 839,
                            "end": 843
                          },
                          "ctxt": 3,
                          "value": "args",
                          "optional": false
                        }
                      }
                    ],
                    "typeArguments": null
                  }
                }
              ]
            },
            "generator": false,
            "async": false,
            "typeParameters": null,
            "returnType": null
          },
          "definite": false
        }
      ]
    }
  ],
  "interpreter": null
}